my_algorithm/__init__.py
my_algorithm/swap.py
my_algorithm_package-0.1.0.dist-info/LICENSE.txt
my_algorithm_package-0.1.0.dist-info/METADATA
my_algorithm_package-0.1.0.dist-info/WHEEL
my_algorithm_package-0.1.0.dist-info/top_level.txt
my_algorithm_package-0.1.0.dist-info/RECORD
