Metadata-Version: 2.2
Name: my_algorithm_package
Version: 0.1.0
Summary: A simple package to swap two values.
Home-page: https://github.com/yourusername/my_algorithm_package
Author: Your Name
Author-email: your.email@example.com
Classifier: Programming Language :: Python :: 3
Classifier: License :: OSI Approved :: MIT License
Classifier: Operating System :: OS Independent
Requires-Python: >=3.7
License-File: LICENSE.txt
